sawatabi/__init__.py
sawatabi/__version__.py
sawatabi/base_mixin.py
sawatabi/constants.py
sawatabi/algorithm/__init__.py
sawatabi/algorithm/abstract_algorithm.py
sawatabi/algorithm/attenuation.py
sawatabi/algorithm/delta.py
sawatabi/algorithm/incremental.py
sawatabi/algorithm/io.py
sawatabi/algorithm/partial.py
sawatabi/algorithm/window.py
sawatabi/model/__init__.py
sawatabi/model/abstract_model.py
sawatabi/model/logical_model.py
sawatabi/model/physical_model.py
sawatabi/model/constraint/__init__.py
sawatabi/model/constraint/abstract_constraint.py
sawatabi/model/constraint/equality_constraint.py
sawatabi/model/constraint/n_hot_constraint.py
sawatabi/model/constraint/zero_or_one_hot_constraint.py
sawatabi/solver/__init__.py
sawatabi/solver/abstract_solver.py
sawatabi/solver/dwave_solver.py
sawatabi/solver/local_solver.py
sawatabi/solver/optigan_solver.py
sawatabi/solver/sawatabi_solver.py
sawatabi/utils/__init__.py
sawatabi/utils/functions.py
sawatabi/utils/npp.py
sawatabi/utils/profile.py
sawatabi/utils/time.py
sawatabi-0.0.3.dist-info/LICENSE
sawatabi-0.0.3.dist-info/METADATA
sawatabi-0.0.3.dist-info/WHEEL
sawatabi-0.0.3.dist-info/top_level.txt
sawatabi-0.0.3.dist-info/RECORD
