Metadata-Version: 2.1
Name: sawatabi
Version: 0.0.3
Summary: Sawatabi is an application framework to develop and run stream-data-oriented Ising applications with quantum annealing.
Home-page: https://github.com/kotarot/sawatabi
Author: Kotaro Terada
Author-email: kotarot@apache.org
License: Apache 2.0
Keywords: python streaming stream-processing ising-model ising quantum-annealing annealing
Platform: UNKNOWN
Classifier: Development Status :: 4 - Beta
Classifier: Intended Audience :: End Users/Desktop
Classifier: License :: OSI Approved :: Apache Software License
Classifier: Programming Language :: Python :: 3.7
Classifier: Programming Language :: Python :: 3.8
Classifier: Topic :: Software Development :: Libraries
Classifier: Topic :: Software Development :: Libraries :: Python Modules
Requires-Dist: apache-beam (<3.0.0,>=2.26.0)
Requires-Dist: apache-beam[gcp] (<3.0.0,>=2.26.0)
Requires-Dist: dwave-system (<2.0.0,>=1.2.1)
Requires-Dist: dwave-neal (<1.0.0,>=0.5.6)
Requires-Dist: pandas (<2.0.0,>=1.1.4)
Requires-Dist: pyqubo (<1.0.0,>=0.4.0)
Requires-Dist: PyYAML (<6.0.0,>=5.3.1)
Provides-Extra: dev
Requires-Dist: apache-beam[interactive] (<3.0.0,>=2.26.0) ; extra == 'dev'
Requires-Dist: pytest (<7.0.0,>=6.1.2) ; extra == 'dev'
Requires-Dist: pytest-cov (<3.0.0,>=2.10.1) ; extra == 'dev'
Requires-Dist: pytest-mock (<4.0.0,>=3.3.1) ; extra == 'dev'
Requires-Dist: pytest-timeout (<2.0.0,>=1.4.2) ; extra == 'dev'
Requires-Dist: black (<21.0,>=20.8b1) ; extra == 'dev'
Requires-Dist: flake8 (<4.0.0,>=3.8.4) ; extra == 'dev'
Requires-Dist: isort (<6.0.0,>=5.6.4) ; extra == 'dev'
Requires-Dist: mypy (<1.0,>=0.800) ; extra == 'dev'
Requires-Dist: snakeviz (<3.0.0,>=2.1.0) ; extra == 'dev'
Requires-Dist: geopy (<3.0.0,>=2.0.0) ; extra == 'dev'
